backup_reminder/assets/logo.svg
backup_reminder/checker.py
backup_reminder/cli.py
backup_reminder/generator/__init__.py
backup_reminder/generator/templates/last-backup.yaml.jinja
backup_reminder-0.0.5.dist-info/LICENSE
backup_reminder-0.0.5.dist-info/METADATA
backup_reminder-0.0.5.dist-info/WHEEL
backup_reminder-0.0.5.dist-info/entry_points.txt
backup_reminder-0.0.5.dist-info/RECORD
