Metadata-Version: 2.1
Name: backup-reminder
Version: 0.0.5
Summary: 
Home-page: https://github.com/groovytron/bare
License: MIT
Author: Julien M'Poy
Requires-Python: >=3.12,<4.0
Classifier: License :: OSI Approved :: MIT License
Classifier: Programming Language :: Python :: 3
Classifier: Programming Language :: Python :: 3.12
Requires-Dist: click (>=8.1.7,<9.0.0)
Requires-Dist: jinja2 (>=3.1.4,<4.0.0)
Requires-Dist: notify-py (>=0.3.43,<0.4.0)
Requires-Dist: pyyaml (>=6.0.2,<7.0.0)
Project-URL: Documentation, https://github.com/groovytron/bare/blob/main/README.md
Project-URL: Repository, https://github.com/groovytron/bare
